fortipass/__init__.py
fortipass/validator.py
FortiPassValidator-1.0.1.dist-info/METADATA
FortiPassValidator-1.0.1.dist-info/WHEEL
FortiPassValidator-1.0.1.dist-info/top_level.txt
FortiPassValidator-1.0.1.dist-info/RECORD
