Metadata-Version: 2.1
Name: FortiPassValidator
Version: 1.0.1
Summary: A Python library for validating passwords with customizable rules.
Home-page: https://github.com/ahmad18189/FortiPassValidator
Author: Ahmed Abdelrahman
Author-email: ahmad18189@gmail.com
Classifier: Programming Language :: Python :: 3
Classifier: License :: OSI Approved :: MIT License
Classifier: Operating System :: OS Independent
Requires-Python: >=3.6
Requires-Dist: profanity-check==1.0.3
